MANIFEST.in
README.md
setup.cfg
setup.py
versioneer.py
cloud_genesis.egg-info/PKG-INFO
cloud_genesis.egg-info/SOURCES.txt
cloud_genesis.egg-info/dependency_links.txt
cloud_genesis.egg-info/requires.txt
cloud_genesis.egg-info/top_level.txt
genesis/__init__.py
genesis/__main__.py
genesis/_version.py
genesis/bulk_statistics/__init__.py
genesis/bulk_statistics/__main__.py
genesis/bulk_statistics/area_fraction_profile.py
genesis/bulk_statistics/cross_correlation_with_height.py
genesis/bulk_statistics/height_dist_plot.py
genesis/bulk_statistics/vertical_flux.py
genesis/length_scales/__init__.py
genesis/length_scales/__main__.py
genesis/length_scales/variability.py
genesis/length_scales/cumulant/__init__.py
genesis/length_scales/cumulant/calc.py
genesis/length_scales/cumulant/sections.py
genesis/length_scales/cumulant/vertical_profile/__init__.py
genesis/length_scales/cumulant/vertical_profile/calc.py
genesis/length_scales/cumulant/vertical_profile/plot.py
genesis/length_scales/model_fitting/__init__.py
genesis/length_scales/model_fitting/exponential_fit.py
genesis/length_scales/model_fitting/pystan_cache.py
genesis/length_scales/model_fitting/utils.py
genesis/objects/__init__.py
genesis/objects/__main__.py
genesis/objects/filter.py
genesis/objects/flux_contribution.py
genesis/objects/identify.py
genesis/objects/integral_properties.py
genesis/objects/integrate.py
genesis/objects/map_property.py
genesis/objects/minkowski_scales.py
genesis/objects/property_filters.py
genesis/objects/render.py
genesis/objects/render_vispy.py
genesis/objects/to_mask.py
genesis/objects/models/__init__.py
genesis/objects/models/parcel_rise.py
genesis/objects/plots/__init__.py
genesis/objects/plots/outline.py
genesis/objects/projected_2d/__init__.py
genesis/objects/projected_2d/aggregation.py
genesis/objects/projected_2d/extraction.py
genesis/objects/projected_2d/filter.py
genesis/objects/projected_2d/object_set.py
genesis/objects/projected_2d/object_types.py
genesis/objects/projected_2d/operations.py
genesis/objects/projected_2d/utils.py
genesis/objects/projected_2d/variables.py
genesis/objects/synthetic/__init__.py
genesis/objects/synthetic/discrete.py
