Metadata-Version: 2.1
Name: cloud-genesis
Version: 0.3.2
Summary: GENESIS toolkit for analysing coherent structures in atmospheric flows
Home-page: https://github.com/leifdenby/genesis
Author: Leif Denby
Author-email: leif@denby.eu
License: UNKNOWN
Platform: UNKNOWN
Provides-Extra: test
Provides-Extra: lint
Provides-Extra: dev
